[
  {
    "id": "heavy_corrugated_carton",
    "name": "重型瓦楞纸箱",
    "keywords": ["重型纸箱", "加厚纸箱", "出口纸箱", "重货包装"],
    "useCases": ["机械配件", "电机设备", "汽车零部件", "五金模具"],
    "sellingPoints": ["按重量和运输线路定制楞型", "可搭配护角和内衬", "降低木箱熏蒸和仓储成本"]
  },
  {
    "id": "honeycomb_carton",
    "name": "蜂窝纸箱",
    "keywords": ["蜂窝纸箱", "蜂窝围板箱", "蜂窝板包装", "缓冲包装"],
    "useCases": ["家电", "陶瓷卫浴", "精密设备", "大件易损品"],
    "sellingPoints": ["抗压缓冲更稳定", "重量轻便于搬运", "适合替代部分木箱方案"]
  },
  {
    "id": "paper_edge_protector",
    "name": "纸护角",
    "keywords": ["纸护角", "护边条", "打包护角", "托盘护角"],
    "useCases": ["板材", "卷材", "门窗", "托盘集装"],
    "sellingPoints": ["防止边角压伤", "提升打包带受力稳定性", "支持长度和厚度定制"]
  },
  {
    "id": "paper_pallet",
    "name": "纸托盘",
    "keywords": ["纸托盘", "蜂窝纸托盘", "免熏蒸托盘", "出口托盘"],
    "useCases": ["出口货物", "轻量化仓储", "电商大件", "工厂周转"],
    "sellingPoints": ["免熏蒸", "轻量可回收", "按动载静载要求设计"]
  },
  {
    "id": "wooden_box_replacement",
    "name": "替代木箱包装",
    "keywords": ["替代木箱", "纸箱代木箱", "免熏蒸包装", "降本包装"],
    "useCases": ["出口设备", "重型零部件", "项目制发货", "整车运输"],
    "sellingPoints": ["减少熏蒸和木材成本", "缩短包装准备周期", "便于印刷和品牌展示"]
  }
]
